elicited/__init__.py
elicited-0.0.5.dist-info/LICENSE
elicited-0.0.5.dist-info/METADATA
elicited-0.0.5.dist-info/WHEEL
elicited-0.0.5.dist-info/top_level.txt
elicited-0.0.5.dist-info/RECORD
