Metadata-Version: 2.1
Name: elicited
Version: 0.0.5
Summary: Helpers for expert elicitation into distributions.
Home-page: https://github.com/magoo/elicitation
Author: Ryan McGeehan
Author-email: elicited@r10n.com
License: UNKNOWN
Project-URL: Bug Tracker, https://github.com/magoo/elicitation/issues
Platform: UNKNOWN
Classifier: Programming Language :: Python :: 3
Classifier: License :: OSI Approved :: MIT License
Classifier: Operating System :: OS Independent
Requires-Python: >=3.6
License-File: LICENSE
Requires-Dist: numpy
Requires-Dist: scipy
